README.rst
setup.cfg
setup.py
speakers/__init__.py
speakers/bus.py
speakers/handy.py
speakers.egg-info/PKG-INFO
speakers.egg-info/SOURCES.txt
speakers.egg-info/dependency_links.txt
speakers.egg-info/top_level.txt