Metadata-Version: 1.0
Name: speakers
Version: 0.1.0
Summary: Simple signal system for python
Home-page: http://github.com/gabrielfalcao/speakers
Author: Gabriel Falcao
Author-email: gabriel@nacaolivre.org
License: UNKNOWN
Platform: UNKNOWN
